datajudge/__init__.py
datajudge/_engines.py
datajudge/condition.py
datajudge/data_source.py
datajudge/db_access.py
datajudge/formatter.py
datajudge/py.typed
datajudge/pytest_integration.py
datajudge/requirements.py
datajudge/utils.py
datajudge/constraints/__init__.py
datajudge/constraints/base.py
datajudge/constraints/column.py
datajudge/constraints/date.py
datajudge/constraints/groupby.py
datajudge/constraints/interval.py
datajudge/constraints/miscs.py
datajudge/constraints/nrows.py
datajudge/constraints/numeric.py
datajudge/constraints/row.py
datajudge/constraints/stats.py
datajudge/constraints/uniques.py
datajudge/constraints/varchar.py
datajudge-1.13.0.dist-info/licenses/LICENSE
datajudge-1.13.0.dist-info/WHEEL
datajudge-1.13.0.dist-info/METADATA
datajudge-1.13.0.dist-info/RECORD
