Metadata-Version: 2.4
Name: datajudge
Version: 1.13.0
Summary: datajudge allows to assess  whether data from database complies with referenceinformation.
Keywords: test,databases,validation
Author-email: "QuantCo, Inc." <noreply@quantco.com>
Requires-Python: >=3.10
Classifier: License :: OSI Approved :: BSD License
Classifier: Operating System :: OS Independent
Classifier: Programming Language :: Python :: 3
Classifier: Programming Language :: Python :: 3.10
Classifier: Programming Language :: Python :: 3.11
Classifier: Programming Language :: Python :: 3.12
Classifier: Programming Language :: Python :: 3.13
Classifier: Programming Language :: Python :: 3.14
Classifier: Topic :: Database
License-File: LICENSE
Requires-Dist: sqlalchemy >=1.4
Requires-Dist: scipy
Requires-Dist: colorama
Project-URL: Source, https://github.com/quantco/datajudge
